pyccmc/__init__.py
pyccmc/api.py
pyccmc/apidocs.py
pyccmc/cli.py
pyccmc-0.0.3.dist-info/LICENSE
pyccmc-0.0.3.dist-info/METADATA
pyccmc-0.0.3.dist-info/WHEEL
pyccmc-0.0.3.dist-info/entry_points.txt
pyccmc-0.0.3.dist-info/top_level.txt
pyccmc-0.0.3.dist-info/RECORD
