Metadata-Version: 2.1
Name: pyccmc
Version: 0.0.3
Summary: Download from CC Mixter
Home-page: https://tigabeatz.net
Author: tigabeatz
Author-email: tigabeatz@cccwi.de
Classifier: Programming Language :: Python :: 3
Classifier: License :: OSI Approved :: GNU General Public License v3 (GPLv3)
Classifier: Operating System :: OS Independent
Classifier: Development Status :: 4 - Beta
Requires-Python: >=3.6
License-File: LICENSE
Requires-Dist: requests
Requires-Dist: tqdm
Requires-Dist: colorama
Requires-Dist: fake-useragent
Requires-Dist: browser-cookie3
